[
{
"company_name": "Outreach",
"job_title": "Software Engineering Internship - Summer 2023",
"linkedin_job_url_cleaned": "https://www.linkedin.com/jobs/view/software-engineering-internship-summer-2023-at-outreach-3273268309",
"job_location": "Seattle, WA",
"posted_date": "2022-10-12",
"Posted_date_int": 20221012,
"Readme_update": ""
},
{
"company_name": "Outreach",
"job_title": "Software Engineering Internship - Summer 2023",
"linkedin_job_url_cleaned": "https://www.linkedin.com/jobs/view/software-engineering-internship-summer-2023-at-outreach-3273265693",
"job_location": "Indianapolis, IN",
"posted_date": "2022-10-12",
"Posted_date_int": 20221012,
"Readme_update": ""
},
{
"company_name": "PayPal",
"job_title": "Data Analyst Intern",
"linkedin_job_url_cleaned": "https://www.linkedin.com/jobs/view/data-analyst-intern-at-paypal-3273299422",
"job_location": "San Jose, CA",
"posted_date": "2022-10-12",
"Posted_date_int": 20221012,
"Readme_update": ""
},
{
"company_name": "TD Auto Finance",
"job_title": "2023 Summer Internship Program – Software Engineer",
"linkedin_job_url_cleaned": "https://www.linkedin.com/jobs/view/2023-summer-internship-program-%E2%80%93-software-engineer-at-td-auto-finance-3303248500",
"job_location": "Mt. Laurel, NJ",
"posted_date": "2022-10-08",
"Posted_date_int": 20221008,
"Readme_update": ""
},
{
"company_name": "Delta Air Lines",
"job_title": "Intern, Revenue Technology - Data Analytics (Summer 2023)",
"linkedin_job_url_cleaned": "https://www.linkedin.com/jobs/view/intern-revenue-technology-data-analytics-summer-2023-at-delta-air-lines-3303197083",
"job_location": "Atlanta, GA",
"posted_date": "2022-10-05",
"Posted_date_int": 20221005,
"Readme_update": ""
},
{
"company_name": "Outreach",
"job_title": "Software Engineering Internship - Summer 2023 (Seattle Based)",
"linkedin_job_url_cleaned": "https://www.linkedin.com/jobs/view/software-engineering-internship-summer-2023-seattle-based-at-outreach-3280646022",
"job_location": "Atlanta, GA",
"posted_date": "2022-09-28",
"Posted_date_int": 20220928,
"Readme_update": ""
},
{
"company_name": "PayPal",
"job_title": "Data Analyst Intern",
"linkedin_job_url_cleaned": "https://www.linkedin.com/jobs/view/data-analyst-intern-at-paypal-3280601821",
"job_location": "Buffalo-Niagara Falls Area",
"posted_date": "2022-09-28",
"Posted_date_int": 20220928,
"Readme_update": ""
},
{
"company_name": "PayPal",
"job_title": "Data Analyst Intern",
"linkedin_job_url_cleaned": "https://www.linkedin.com/jobs/view/data-analyst-intern-at-paypal-3280608127",
"job_location": "Chicago, IL",
"posted_date": "2022-09-28",
"Posted_date_int": 20220928,
"Readme_update": ""
},
{
"company_name": "PayPal",
"job_title": "Data Analyst Intern",
"linkedin_job_url_cleaned": "https://www.linkedin.com/jobs/view/data-analyst-intern-at-paypal-3280602572",
"job_location": "Austin, TX",
"posted_date": "2022-09-28",
"Posted_date_int": 20220928,
"Readme_update": ""
},
{
"company_name": "PayPal",
"job_title": "Data Analyst Intern",
"linkedin_job_url_cleaned": "https://www.linkedin.com/jobs/view/data-analyst-intern-at-paypal-3280604481",
"job_location": "Timonium, MD",
"posted_date": "2022-09-28",
"Posted_date_int": 20220928,
"Readme_update": ""
},
{
"company_name": "Delta Air Lines",
"job_title": "Intern, IT - Infrastructure and Reliability (Summer 2023)",
"linkedin_job_url_cleaned": "https://www.linkedin.com/jobs/view/intern-it-infrastructure-and-reliability-summer-2023-at-delta-air-lines-3285885153",
"job_location": "Atlanta, GA",
"posted_date": "2022-09-23",
"Posted_date_int": 20220923,
"Readme_update": ""
},
{
"company_name": "Delta Air Lines",
"job_title": "Intern, IT - Enterprise Technology (Summer 2023)",
"linkedin_job_url_cleaned": "https://www.linkedin.com/jobs/view/intern-it-enterprise-technology-summer-2023-at-delta-air-lines-3285884233",
"job_location": "Atlanta, GA",
"posted_date": "2022-09-23",
"Posted_date_int": 20220923,
"Readme_update": ""
},
{
"company_name": "Lockheed Martin",
"job_title": "Software Engineering Internship",
"linkedin_job_url_cleaned": "https://www.linkedin.com/jobs/view/software-engineering-internship-at-lockheed-martin-3270592196",
"job_location": "Colorado Springs, CO",
"posted_date": "2022-09-19",
"Posted_date_int": 20220919,
"Readme_update": ""
},
{
"company_name": "TD",
"job_title": "2023 Summer Internship Program – Software Engineer",
"linkedin_job_url_cleaned": "https://www.linkedin.com/jobs/view/2023-summer-internship-program-%E2%80%93-software-engineer-at-td-3314896080",
"job_location": "New York, NY",
"posted_date": "2022-09-19",
"Posted_date_int": 20220919,
"Readme_update": ""
},
{
"company_name": "Lockheed Martin",
"job_title": "Software Engineer - Intern",
"linkedin_job_url_cleaned": "https://www.linkedin.com/jobs/view/software-engineer-intern-at-lockheed-martin-3267321922",
"job_location": "Fort Worth, TX",
"posted_date": "2022-09-15",
"Posted_date_int": 20220915,
"Readme_update": ""
},
{
"company_name": "Lockheed Martin",
"job_title": "Software Engineering Internship",
"linkedin_job_url_cleaned": "https://www.linkedin.com/jobs/view/software-engineering-internship-at-lockheed-martin-3267326479",
"job_location": "Colorado Springs, CO",
"posted_date": "2022-09-15",
"Posted_date_int": 20220915,
"Readme_update": ""
},
{
"company_name": "Lockheed Martin",
"job_title": "Software Engineer - Intern",
"linkedin_job_url_cleaned": "https://www.linkedin.com/jobs/view/software-engineer-intern-at-lockheed-martin-3267321918",
"job_location": "Fort Worth, TX",
"posted_date": "2022-09-15",
"Posted_date_int": 20220915,
"Readme_update": ""
},
{
"company_name": "Lockheed Martin",
"job_title": "Software Quality Engineer - Intern",
"linkedin_job_url_cleaned": "https://www.linkedin.com/jobs/view/software-quality-engineer-intern-at-lockheed-martin-3267321920",
"job_location": "Fort Worth, TX",
"posted_date": "2022-09-15",
"Posted_date_int": 20220915,
"Readme_update": ""
},
{
"company_name": "Leidos",
"job_title": "Semester-Long Software Engineering Intern",
"linkedin_job_url_cleaned": "https://www.linkedin.com/jobs/view/semester-long-software-engineering-intern-at-leidos-3272099213",
"job_location": "Reston, VA",
"posted_date": "2022-09-15",
"Posted_date_int": 20220915,
"Readme_update": ""
},
{
"company_name": "Lockheed Martin",
"job_title": "Software Engineer - Summer Intern",
"linkedin_job_url_cleaned": "https://www.linkedin.com/jobs/view/software-engineer-summer-intern-at-lockheed-martin-3265158710",
"job_location": "Force, PA",
"posted_date": "2022-09-14",
"Posted_date_int": 20220914,
"Readme_update": ""
},
{
"company_name": "TD",
"job_title": "2023 Summer Internship Program – Software Engineer",
"linkedin_job_url_cleaned": "https://www.linkedin.com/jobs/view/2023-summer-internship-program-%E2%80%93-software-engineer-at-td-3307150352",
"job_location": "Mt. Laurel, NJ",
"posted_date": "2022-09-13",
"Posted_date_int": 20220913,
"Readme_update": ""
},
{
"company_name": "TD",
"job_title": "2023 Summer Internship Program – Software Engineer",
"linkedin_job_url_cleaned": "https://www.linkedin.com/jobs/view/2023-summer-internship-program-%E2%80%93-software-engineer-at-td-3306552670",
"job_location": "Falmouth, ME",
"posted_date": "2022-09-13",
"Posted_date_int": 20220913,
"Readme_update": ""
},
{
"company_name": "TD",
"job_title": "2023 Summer Internship Program – Software Engineer",
"linkedin_job_url_cleaned": "https://www.linkedin.com/jobs/view/2023-summer-internship-program-%E2%80%93-software-engineer-at-td-3306556349",
"job_location": "Hamden, CT",
"posted_date": "2022-09-13",
"Posted_date_int": 20220913,
"Readme_update": ""
},
{
"company_name": "TD",
"job_title": "2023 Summer Internship Program – Software Engineer",
"linkedin_job_url_cleaned": "https://www.linkedin.com/jobs/view/2023-summer-internship-program-%E2%80%93-software-engineer-at-td-3270288782",
"job_location": "Springfield, MD",
"posted_date": "2022-09-02",
"Posted_date_int": 20220902,
"Readme_update": ""
},
{
"company_name": "TD",
"job_title": "2023 Summer Internship Program – Software Engineer",
"linkedin_job_url_cleaned": "https://www.linkedin.com/jobs/view/2023-summer-internship-program-%E2%80%93-software-engineer-at-td-3262493364",
"job_location": "Port St Lucie, FL",
"posted_date": "2022-09-02",
"Posted_date_int": 20220902,
"Readme_update": ""
}
]